setup.py
P1tr.egg-info/PKG-INFO
P1tr.egg-info/SOURCES.txt
P1tr.egg-info/dependency_links.txt
P1tr.egg-info/entry_points.txt
P1tr.egg-info/requires.txt
P1tr.egg-info/top_level.txt
p1tr/__init__.py
p1tr/config.py
p1tr/helpers.py
p1tr/logwrap.py
p1tr/p1tr.py
p1tr/plugin.py
p1tr/test.py
plugins/__init__.py
plugins/authdefault/__init__.py
plugins/authdefault/authdefault.py
plugins/authnickserv/__init__.py
plugins/authnickserv/authnickserv.py
plugins/hello/__init__.py
plugins/hello/hello.py
plugins/hello/hello_test.py
plugins/help/__init__.py
plugins/help/help.py
plugins/irc/__init__.py
plugins/irc/irc.py
plugins/karma/__init__.py
plugins/karma/karma.py
plugins/logger/__init__.py
plugins/logger/logger.py
plugins/memo/__init__.py
plugins/memo/memo.py
plugins/seen/__init__.py
plugins/seen/seen.py
plugins/seen/seen_test.py
plugins/unix/__init__.py
plugins/unix/unix.py
plugins/wordtracker/__init__.py
plugins/wordtracker/wordtracker.py