Metadata-Version: 1.0
Name: P1tr
Version: 0.1beta
Summary: A modular irc bot.
Home-page: https://github.com/howard/p1tr-tng
Author: Christian Ortner
Author-email: chris.ortner@gmail.com
License: MIT
Keywords: plugin irc bot
Platform: UNKNOWN
